[
  {
    "id": "mix-001",
    "title": "AintSaint Opening Mix",
    "talentId": "talent-01",
    "talentName": "DJ Talent 01",
    "eoOwner": "SinnersNight",
    "platform": "YouTube",
    "contentType": "Mix",
    "genres": ["Baile Funk", "Jersey Club"],
    "thumbnail": "assets/img/mixes/mix-001.jpg",
    "url": "https://youtube.com/",
    "embedUrl": "https://www.youtube.com/embed/VIDEO_ID",
    "duration": "30:00",
    "publishedAt": "2026-07-05",
    "featured": true,
    "status": "Published"
  },
  {
    "id": "mix-002",
    "title": "Afro Groove Night Session",
    "talentId": "talent-02",
    "talentName": "DJ Talent 02",
    "eoOwner": "SinnersNight",
    "platform": "SoundCloud",
    "contentType": "Studio Mix",
    "genres": ["Afro House", "Tech House", "Hard Groove"],
    "thumbnail": "assets/img/mixes/mix-002.jpg",
    "url": "https://soundcloud.com/",
    "embedUrl": "",
    "duration": "42:10",
    "publishedAt": "2026-07-03",
    "featured": false,
    "status": "Published"
  },
  {
    "id": "mix-003",
    "title": "Bass Pressure Club Cut",
    "talentId": "talent-03",
    "talentName": "DJ Talent 03",
    "eoOwner": "SinnersNight",
    "platform": "TikTok",
    "contentType": "Short Video",
    "genres": ["Trap", "Drum & Bass", "Bass House"],
    "thumbnail": "assets/img/mixes/mix-placeholder.jpg",
    "url": "https://tiktok.com/",
    "embedUrl": "",
    "duration": "00:58",
    "publishedAt": "2026-06-28",
    "featured": false,
    "status": "Published"
  },
  {
    "id": "mix-004",
    "title": "Local Bounce Starter Pack",
    "talentId": "talent-04",
    "talentName": "DJ Talent 04",
    "eoOwner": "WestSidePeople",
    "platform": "YouTube",
    "contentType": "Live Set",
    "genres": ["Breakbeat", "Funkot", "Indo Bounce"],
    "thumbnail": "assets/img/mixes/mix-placeholder.jpg",
    "url": "https://youtube.com/",
    "embedUrl": "https://www.youtube.com/embed/VIDEO_ID",
    "duration": "35:20",
    "publishedAt": "2026-06-25",
    "featured": true,
    "status": "Published"
  },
  {
    "id": "mix-005",
    "title": "Hardfunk Street Signal",
    "talentId": "talent-05",
    "talentName": "DJ Talent 05",
    "eoOwner": "WestSidePeople",
    "platform": "Instagram",
    "contentType": "Reel",
    "genres": ["Hardfunk", "Jungle Dutch", "Dutch Boxing"],
    "thumbnail": "assets/img/mixes/mix-placeholder.jpg",
    "url": "https://instagram.com/",
    "embedUrl": "",
    "duration": "01:20",
    "publishedAt": "2026-06-22",
    "featured": false,
    "status": "Published"
  },
  {
    "id": "mix-006",
    "title": "Campursari Switch Tape",
    "talentId": "talent-06",
    "talentName": "DJ Talent 06",
    "eoOwner": "WestSidePeople",
    "platform": "SoundCloud",
    "contentType": "Mix",
    "genres": ["Campursari Switch", "Pantura Style", "House Kota"],
    "thumbnail": "assets/img/mixes/mix-placeholder.jpg",
    "url": "https://soundcloud.com/",
    "embedUrl": "",
    "duration": "28:44",
    "publishedAt": "2026-06-18",
    "featured": false,
    "status": "Published"
  },
  {
    "id": "mix-007",
    "title": "Local x Global Switch Vol. 1",
    "talentId": "talent-07",
    "talentName": "DJ Talent 07",
    "eoOwner": "Hybrid",
    "platform": "YouTube",
    "contentType": "Visualizer",
    "genres": ["Local x Global Switch", "Baile Funk", "Breakbeat"],
    "thumbnail": "assets/img/mixes/mix-placeholder.jpg",
    "url": "https://youtube.com/",
    "embedUrl": "https://www.youtube.com/embed/VIDEO_ID",
    "duration": "24:30",
    "publishedAt": "2026-06-15",
    "featured": true,
    "status": "Published"
  },
  {
    "id": "mix-008",
    "title": "SinnersNight Behind The Booth",
    "talentId": "talent-01",
    "talentName": "DJ Talent 01",
    "eoOwner": "SinnersNight",
    "platform": "Instagram",
    "contentType": "Behind The Scene",
    "genres": ["Global Club", "Tech House"],
    "thumbnail": "assets/img/mixes/mix-placeholder.jpg",
    "url": "https://instagram.com/",
    "embedUrl": "",
    "duration": "01:05",
    "publishedAt": "2026-06-11",
    "featured": false,
    "status": "Published"
  },
  {
    "id": "mix-009",
    "title": "WestSidePeople Crowd Recap",
    "talentId": "talent-04",
    "talentName": "DJ Talent 04",
    "eoOwner": "WestSidePeople",
    "platform": "TikTok",
    "contentType": "Event Recap",
    "genres": ["Breakbeat", "Funkot", "Local Remix Culture"],
    "thumbnail": "assets/img/mixes/mix-placeholder.jpg",
    "url": "https://tiktok.com/",
    "embedUrl": "",
    "duration": "00:45",
    "publishedAt": "2026-06-06",
    "featured": false,
    "status": "Published"
  },
  {
    "id": "mix-010",
    "title": "Draft Testing Mix",
    "talentId": "talent-07",
    "talentName": "DJ Talent 07",
    "eoOwner": "Hybrid",
    "platform": "YouTube",
    "contentType": "Mix",
    "genres": ["Local x Global Switch"],
    "thumbnail": "assets/img/mixes/mix-placeholder.jpg",
    "url": "https://youtube.com/",
    "embedUrl": "",
    "duration": "12:00",
    "publishedAt": "2026-06-01",
    "featured": false,
    "status": "Hidden"
  }
]



